loggram/__init__.py
loggram/loggram.py
loggram-1.0.2.dist-info/LICENSE
loggram-1.0.2.dist-info/METADATA
loggram-1.0.2.dist-info/WHEEL
loggram-1.0.2.dist-info/top_level.txt
loggram-1.0.2.dist-info/RECORD
