Metadata-Version: 2.1
Name: loggram
Version: 1.0.2
Summary: A package for sending logs to Telegram channels
Home-page: https://github.com/Ilia-Abolhasani/loggram
Author: Ilia Abolhasani
Author-email: abolhasani.eliya@gmail.com
Classifier: Programming Language :: Python :: 3
Classifier: License :: OSI Approved :: MIT License
Classifier: Operating System :: OS Independent
Requires-Python: >=3.6
License-File: LICENSE
Requires-Dist: python-telegram-bot
